prophecy_deploy_cli_config/__init__.py
prophecy_deploy_cli_config/deploy-cli-standalone-v1.0.1-jpmc-bec9ef6/README.md
prophecy_deploy_cli_config/deploy-cli-standalone-v1.0.1-jpmc-bec9ef6/deploy-cli.sh
prophecy_deploy_cli_config/deploy-cli-standalone-v1.0.1-jpmc-bec9ef6/config/embedded.yml
prophecy_deploy_cli_config-1.0.1.dist-info/METADATA
prophecy_deploy_cli_config-1.0.1.dist-info/WHEEL
prophecy_deploy_cli_config-1.0.1.dist-info/top_level.txt
prophecy_deploy_cli_config-1.0.1.dist-info/RECORD
